[
    {
        "rule_id": "RL-US-001",
        "rule_name": "《国际紧急经济权力法》",
        "rule_domain": "经济制裁",
        "rule_type": "红线",
        "rule_class": "联邦法律",
        "enacted_year": 1977,
        "action_type": "经济制裁",
        "act": "国际紧急经济权力法",
        "section": "第201条",
        "violation_action": "未经总统授权，对外国政府或实体实施经济制裁、冻结资产或限制金融交易",
        "handling": "直接剔除"
    },
    {
        "rule_id": "RL-US-002",
        "rule_name": "《国防生产法》",
        "rule_domain": "国家安全",
        "rule_type": "红线",
        "rule_class": "联邦法律",
        "enacted_year": 1950,
        "action_type": "产业控制",
        "act": "国防生产法",
        "section": "第301条",
        "violation_action": "将涉及国家安全的关键产业控制权转移给外国政府或受其控制的实体",
        "handling": "直接剔除"
    },
    {
        "rule_id": "RL-US-003",
        "rule_name": "《对外援助法》",
        "rule_domain": "对外政策",
        "rule_type": "底线",
        "rule_class": "联邦法律",
        "enacted_year": 1961,
        "action_type": "对外援助",
        "act": "对外援助法",
        "section": "第601条",
        "violation_action": "向违反人权、支持恐怖主义或从事核扩散的国家或实体提供援助",
        "handling": "待修正"
    },
    {
        "rule_id": "RL-US-004",
        "rule_name": "《武器出口控制法》",
        "rule_domain": "军控",
        "rule_type": "红线",
        "rule_class": "联邦法律",
        "enacted_year": 1976,
        "action_type": "武器出口",
        "act": "武器出口控制法",
        "section": "第3条",
        "violation_action": "未经国务院授权，出口国防物品、服务或相关技术至未获许可的国家",
        "handling": "直接剔除"
    },
    {
        "rule_id": "RL-US-005",
        "rule_name": "《贸易扩展法》",
        "rule_domain": "贸易",
        "rule_type": "底线",
        "rule_class": "联邦法律",
        "enacted_year": 1962,
        "action_type": "关税措施",
        "act": "贸易扩展法",
        "section": "第232条",
        "violation_action": "以国家安全为由滥用关税措施，实施超出必要范围的贸易限制",
        "handling": "待修正"
    },
    {
        "rule_id": "RL-US-006",
        "rule_name": "《联合国宪章》",
        "rule_domain": "国际法",
        "rule_type": "红线",
        "rule_class": "国际条约",
        "enacted_year": 1945,
        "action_type": "军事行动",
        "act": "联合国宪章",
        "section": "第2条第4款",
        "violation_action": "在未获得联合国安理会授权或非出于自卫的情况下，对他国使用武力或威胁使用武力",
        "handling": "直接剔除"
    },
    {
        "rule_id": "RL-US-007",
        "rule_name": "《中导条约》",
        "rule_domain": "军控",
        "rule_type": "底线",
        "rule_class": "国际条约",
        "enacted_year": 1987,
        "action_type": "军备控制",
        "act": "中导条约",
        "section": "第1条",
        "violation_action": "研发、生产、部署或试射射程在500公里至5500公里之间的弹道导弹或巡航导弹",
        "handling": "待修正"
    },
    {
        "rule_id": "RL-US-008",
        "rule_name": "《外国投资风险审查现代化法》",
        "rule_domain": "投资审查",
        "rule_type": "底线",
        "rule_class": "联邦法律",
        "enacted_year": 2018,
        "action_type": "外资审查",
        "act": "外国投资风险审查现代化法",
        "section": "第721条",
        "violation_action": "未向CFIUS申报可能涉及关键技术、基础设施或敏感数据的外国投资交易",
        "handling": "待修正"
    }
]